mycalc/calculator.py
kj20240410-0.0.1.dist-info/LICENSE
kj20240410-0.0.1.dist-info/METADATA
kj20240410-0.0.1.dist-info/WHEEL
kj20240410-0.0.1.dist-info/top_level.txt
kj20240410-0.0.1.dist-info/RECORD
