Metadata-Version: 2.1
Name: kj20240410
Version: 0.0.1
Summary: nice calculator
Author: kim
Classifier: Programming Language :: Python :: 3
License-File: LICENSE
